zmzmdr/__init__.py
zmzmdr/main.py
zmzmdr-0.0.4.dist-info/DESCRIPTION.rst
zmzmdr-0.0.4.dist-info/METADATA
zmzmdr-0.0.4.dist-info/RECORD
zmzmdr-0.0.4.dist-info/WHEEL
zmzmdr-0.0.4.dist-info/entry_points.txt
zmzmdr-0.0.4.dist-info/metadata.json
zmzmdr-0.0.4.dist-info/top_level.txt
