Metadata-Version: 2.0
Name: zmzmdr
Version: 0.0.4
Summary: fish
Home-page: UNKNOWN
Author: fish
Author-email: zmzmdr@gmail.com
License: MIT
Platform: UNKNOWN
Provides-Extra: dev
Provides-Extra: test
